transform_wav.py
transform_wav-0.0.1.dist-info/LICENSE
transform_wav-0.0.1.dist-info/METADATA
transform_wav-0.0.1.dist-info/WHEEL
transform_wav-0.0.1.dist-info/top_level.txt
transform_wav-0.0.1.dist-info/RECORD
