Metadata-Version: 2.1
Name: transform_wav
Version: 0.0.1
Summary: Simple utility to transform wav files
Author-email: Suriya Ganesh <sayyampe@andrew.cmu.edu>
Project-URL: Homepage, https://github.com/suriya-ganesh/transform_wav
Project-URL: Issues, https://github.com/suriya-ganesh/transform_wav/issues
Classifier: Programming Language :: Python :: 3
Classifier: License :: OSI Approved :: MIT License
Classifier: Operating System :: OS Independent
Requires-Python: >=3.8
License-File: LICENSE
